{
	"partitions" : [
		{
			"name" : "Top",
			"pins" : [
				{
					"name" : "clk",
					"strict" : false
				},
				{
					"name" : "rxData[15]",
					"strict" : false
				},
				{
					"name" : "rxData[14]",
					"strict" : false
				},
				{
					"name" : "rxData[13]",
					"strict" : false
				},
				{
					"name" : "rxData[12]",
					"strict" : false
				},
				{
					"name" : "rxData[11]",
					"strict" : false
				},
				{
					"name" : "rxData[10]",
					"strict" : false
				},
				{
					"name" : "rxData[9]",
					"strict" : false
				},
				{
					"name" : "rxData[8]",
					"strict" : false
				},
				{
					"name" : "rxData[7]",
					"strict" : false
				},
				{
					"name" : "rxData[6]",
					"strict" : false
				},
				{
					"name" : "rxData[5]",
					"strict" : false
				},
				{
					"name" : "rxData[4]",
					"strict" : false
				},
				{
					"name" : "rxData[3]",
					"strict" : false
				},
				{
					"name" : "rxData[2]",
					"strict" : false
				},
				{
					"name" : "rxData[1]",
					"strict" : false
				},
				{
					"name" : "rxData[0]",
					"strict" : false
				},
				{
					"name" : "opcode[5]",
					"strict" : false
				},
				{
					"name" : "opcode[4]",
					"strict" : false
				},
				{
					"name" : "opcode[3]",
					"strict" : false
				},
				{
					"name" : "opcode[2]",
					"strict" : false
				},
				{
					"name" : "opcode[1]",
					"strict" : false
				},
				{
					"name" : "opcode[0]",
					"strict" : false
				},
				{
					"name" : "rzData[15]",
					"strict" : false
				},
				{
					"name" : "rzData[14]",
					"strict" : false
				},
				{
					"name" : "rzData[13]",
					"strict" : false
				},
				{
					"name" : "rzData[12]",
					"strict" : false
				},
				{
					"name" : "rzData[11]",
					"strict" : false
				},
				{
					"name" : "rzData[10]",
					"strict" : false
				},
				{
					"name" : "rzData[9]",
					"strict" : false
				},
				{
					"name" : "rzData[8]",
					"strict" : false
				},
				{
					"name" : "rzData[7]",
					"strict" : false
				},
				{
					"name" : "rzData[6]",
					"strict" : false
				},
				{
					"name" : "rzData[5]",
					"strict" : false
				},
				{
					"name" : "rzData[4]",
					"strict" : false
				},
				{
					"name" : "rzData[3]",
					"strict" : false
				},
				{
					"name" : "rzData[2]",
					"strict" : false
				},
				{
					"name" : "rzData[1]",
					"strict" : false
				},
				{
					"name" : "rzData[0]",
					"strict" : false
				},
				{
					"name" : "state[3]",
					"strict" : false
				},
				{
					"name" : "state[2]",
					"strict" : false
				},
				{
					"name" : "state[1]",
					"strict" : false
				},
				{
					"name" : "state[0]",
					"strict" : false
				},
				{
					"name" : "am[1]",
					"strict" : false
				},
				{
					"name" : "am[0]",
					"strict" : false
				},
				{
					"name" : "LEDR[5]",
					"strict" : false
				},
				{
					"name" : "LEDR[4]",
					"strict" : false
				},
				{
					"name" : "LEDR[3]",
					"strict" : false
				},
				{
					"name" : "LEDR[2]",
					"strict" : false
				},
				{
					"name" : "LEDR[1]",
					"strict" : false
				},
				{
					"name" : "LEDR[0]",
					"strict" : false
				},
				{
					"name" : "operand_out[15]",
					"strict" : false
				},
				{
					"name" : "operand_out[14]",
					"strict" : false
				},
				{
					"name" : "operand_out[13]",
					"strict" : false
				},
				{
					"name" : "operand_out[12]",
					"strict" : false
				},
				{
					"name" : "operand_out[11]",
					"strict" : false
				},
				{
					"name" : "operand_out[10]",
					"strict" : false
				},
				{
					"name" : "operand_out[9]",
					"strict" : false
				},
				{
					"name" : "operand_out[8]",
					"strict" : false
				},
				{
					"name" : "operand_out[7]",
					"strict" : false
				},
				{
					"name" : "operand_out[6]",
					"strict" : false
				},
				{
					"name" : "operand_out[5]",
					"strict" : false
				},
				{
					"name" : "operand_out[4]",
					"strict" : false
				},
				{
					"name" : "operand_out[3]",
					"strict" : false
				},
				{
					"name" : "operand_out[2]",
					"strict" : false
				},
				{
					"name" : "operand_out[1]",
					"strict" : false
				},
				{
					"name" : "operand_out[0]",
					"strict" : false
				},
				{
					"name" : "CLOCK_50",
					"strict" : false
				},
				{
					"name" : "KEY[0]",
					"strict" : false
				},
				{
					"name" : "SW[9]",
					"strict" : false
				},
				{
					"name" : "SW[8]",
					"strict" : false
				},
				{
					"name" : "SW[7]",
					"strict" : false
				},
				{
					"name" : "SW[6]",
					"strict" : false
				},
				{
					"name" : "SW[5]",
					"strict" : false
				},
				{
					"name" : "SW[4]",
					"strict" : false
				},
				{
					"name" : "SW[3]",
					"strict" : false
				},
				{
					"name" : "SW[2]",
					"strict" : false
				},
				{
					"name" : "SW[1]",
					"strict" : false
				},
				{
					"name" : "SW[0]",
					"strict" : false
				}
			]
		}
	]
}